deeq/__init__.py
deeq/_version.py
deeq/circuit.py
deeq/decorators.py
deeq/gate.py
deeq/gateset.py
deeq/pauli.py
deeq/typing.py
deeq/utils.py
deeq/vqe.py
deeq/backends/__init__.py
deeq/backends/_numba_backend_impl.py
deeq/backends/backendbase.py
deeq/backends/draw_backend.py
deeq/backends/ibmq_backend.py
deeq/backends/manyqubitgate_fallbacker.py
deeq/backends/numba_backend.py
deeq/backends/numpy_backend.py
deeq/backends/onequbitgate_decomposer.py
deeq/backends/onequbitgate_transpiler.py
deeq/backends/qasm_output_backend.py
deeq/backends/qasm_parser_backend_generator.py
deeq/backends/quimb.py
deeq/backends/sympy_backend.py
deeq/backends/twoqubitgate_transpiler.py
deeq/circuit_funcs/__init__.py
deeq/circuit_funcs/circuit_to_unitary.py
deeq/circuit_funcs/flatten.py
deeq/circuit_funcs/json_serializer.py
deeq/macros/__init__.py
deeq-2.0.3.dist-info/LICENSE
deeq-2.0.3.dist-info/METADATA
deeq-2.0.3.dist-info/WHEEL
deeq-2.0.3.dist-info/top_level.txt
deeq-2.0.3.dist-info/RECORD
